{
  "account": {
    "id": "act_1833510890685857",
    "name": "Unlocked Low Ticket 1",
    "status": "ACTIVE",
    "currency": "USD"
  },
  "period": "today",
  "level": "adset",
  "summary": {
    "total_spend": 83.5,
    "total_purchases": 1,
    "total_revenue_estimated": 0,
    "avg_cpa": 83.5,
    "avg_roas": 0
  },
  "campaigns": [
    {
      "name": "CPAcademia | PixelSuscrip | Ventas | Master ABO | Sistema 5 Creativos | 28 Abril",
      "status": "ACTIVE",
      "objective": "OUTCOME_SALES",
      "daily_budget": null,
      "lifetime_budget": null,
      "budget_remaining": 0
    },
    {
      "name": "CPAcademia | PixelSuscrip | Ventas | CBO | 5Conceptos | 21 Abril Activar",
      "status": "ACTIVE",
      "objective": "OUTCOME_SALES",
      "daily_budget": null,
      "lifetime_budget": null,
      "budget_remaining": 0
    },
    {
      "name": "CPAcademia | PixelSuscrip | Ventas | CBO Test | TopCreatives | 18 Abril",
      "status": "ACTIVE",
      "objective": "OUTCOME_SALES",
      "daily_budget": 50,
      "lifetime_budget": null,
      "budget_remaining": 27.39
    },
    {
      "name": "CPAcademia | PixelSuscrip | Ventas | Master ABO | Empizadropoptotal | 21 Marzo",
      "status": "ACTIVE",
      "objective": "OUTCOME_SALES",
      "daily_budget": null,
      "lifetime_budget": null,
      "budget_remaining": 0
    },
    {
      "name": "CPAcademia | PixelSuscrip | Ventas | Master ABO | Droptotal | 18 Marzo",
      "status": "PAUSED",
      "objective": "OUTCOME_SALES",
      "daily_budget": null,
      "lifetime_budget": null,
      "budget_remaining": 0
    },
    {
      "name": "CPAcademia | PixelSuscrip | Landing Curso. | Ventas | Master ABO | Droptotal | 11 Marzo",
      "status": "PAUSED",
      "objective": "OUTCOME_SALES",
      "daily_budget": null,
      "lifetime_budget": null,
      "budget_remaining": 0
    },
    {
      "name": "CPAcademia | PixelSuscrip | Ventas | Master ABO | Droptotal | 18 Feb",
      "status": "PAUSED",
      "objective": "OUTCOME_SALES",
      "daily_budget": null,
      "lifetime_budget": null,
      "budget_remaining": 0
    },
    {
      "name": "Leads | Lanzamiento Enero 2026 Master ABO | CO | VSL | 19 Enero",
      "status": "PAUSED",
      "objective": "OUTCOME_LEADS",
      "daily_budget": null,
      "lifetime_budget": null,
      "budget_remaining": 0
    }
  ],
  "insights": [
    {
      "campaign_name": "CPAcademia | PixelSuscrip | Ventas | Master ABO | Empizadropoptotal | 21 Marzo",
      "campaign_id": "120241959986740335",
      "adset_name": "USuscri | C | CO | Abierto | 22 marzo",
      "adset_id": "120241959986730335",
      "spend": 22.89,
      "impressions": 2108,
      "reach": 1655,
      "clicks": 34,
      "cpm": 10.858634,
      "cpc": 0.673235,
      "ctr": 1.612903,
      "frequency": 1.273716,
      "purchases": 0,
      "leads": 1,
      "initiate_checkout": 0,
      "add_to_cart": 0,
      "cost_per_purchase": 0,
      "roas": 0
    },
    {
      "campaign_name": "CPAcademia | PixelSuscrip | Ventas | Master ABO | Sistema 5 Creativos | 28 Abril",
      "campaign_id": "120243883867660335",
      "adset_name": "USuscri | C | CO | Abierto | Sistema 5 Creativos | 28 Abril",
      "adset_id": "120243884243490335",
      "spend": 18.19,
      "impressions": 2667,
      "reach": 1803,
      "clicks": 34,
      "cpm": 6.820397,
      "cpc": 0.535,
      "ctr": 1.274841,
      "frequency": 1.479201,
      "purchases": 0,
      "leads": 0,
      "initiate_checkout": 0,
      "add_to_cart": 0,
      "cost_per_purchase": 0,
      "roas": 0
    },
    {
      "campaign_name": "CPAcademia | PixelSuscrip | Ventas | CBO Test | TopCreatives | 18 Abril",
      "campaign_id": "120243369739880335",
      "adset_name": "USuscri | C | CO | Abierto | Clon Broad | 18 Abril",
      "adset_id": "120243369740310335",
      "spend": 17,
      "impressions": 1689,
      "reach": 1400,
      "clicks": 26,
      "cpm": 10.065127,
      "cpc": 0.653846,
      "ctr": 1.539372,
      "frequency": 1.206429,
      "purchases": 0,
      "leads": 0,
      "initiate_checkout": 0,
      "add_to_cart": 0,
      "cost_per_purchase": 0,
      "roas": 0
    },
    {
      "campaign_name": "CPAcademia | PixelSuscrip | Ventas | CBO | 5Conceptos | 21 Abril Activar",
      "campaign_id": "120243497487380335",
      "adset_name": "USuscri | C2 | CO | LAL Compradores | 21 Abril",
      "adset_id": "120243497488670335",
      "spend": 10.22,
      "impressions": 1187,
      "reach": 939,
      "clicks": 35,
      "cpm": 8.609941,
      "cpc": 0.292,
      "ctr": 2.94861,
      "frequency": 1.264111,
      "purchases": 0,
      "leads": 0,
      "initiate_checkout": 0,
      "add_to_cart": 0,
      "cost_per_purchase": 0,
      "roas": 0
    },
    {
      "campaign_name": "CPAcademia | PixelSuscrip | Ventas | CBO | 5Conceptos | 21 Abril Activar",
      "campaign_id": "120243497487380335",
      "adset_name": "USuscri | C5 | CO | Interaccion IG 90d | 21 Abril",
      "adset_id": "120243497513940335",
      "spend": 9.59,
      "impressions": 1314,
      "reach": 816,
      "clicks": 26,
      "cpm": 7.298326,
      "cpc": 0.368846,
      "ctr": 1.978691,
      "frequency": 1.610294,
      "purchases": 0,
      "leads": 2,
      "initiate_checkout": 3,
      "add_to_cart": 0,
      "cost_per_purchase": 0,
      "roas": 0
    },
    {
      "campaign_name": "CPAcademia | PixelSuscrip | Ventas | CBO Test | TopCreatives | 18 Abril",
      "campaign_id": "120243369739880335",
      "adset_name": "USuscri | C | CO | Abierto | LAL Compradores | 18 Abril",
      "adset_id": "120243369742060335",
      "spend": 5.61,
      "impressions": 439,
      "reach": 335,
      "clicks": 25,
      "cpm": 12.779043,
      "cpc": 0.2244,
      "ctr": 5.694761,
      "frequency": 1.310448,
      "purchases": 0,
      "leads": 0,
      "initiate_checkout": 0,
      "add_to_cart": 0,
      "cost_per_purchase": 0,
      "roas": 0
    },
    {
      "campaign_name": "CPAcademia | PixelSuscrip | Ventas | CBO Test | TopCreatives | 18 Abril",
      "campaign_id": "120243369739880335",
      "adset_name": "USuscri | C | CO | Abierto | LAL InitiateCheckout | 18 Abril",
      "adset_id": "120243369743930335",
      "spend": 0,
      "impressions": 0,
      "reach": 0,
      "clicks": 0,
      "cpm": 0,
      "cpc": 0,
      "ctr": 0,
      "frequency": 0,
      "purchases": 1,
      "leads": 1,
      "initiate_checkout": 1,
      "add_to_cart": 0,
      "cost_per_purchase": 0,
      "roas": 0
    }
  ]
}