{
  "account": {
    "id": "act_1833510890685857",
    "name": "Unlocked Low Ticket 1",
    "status": "ACTIVE",
    "currency": "USD"
  },
  "period": "today",
  "level": "adset",
  "summary": {
    "total_spend": 112.53,
    "total_purchases": 3,
    "total_revenue_estimated": 84.62,
    "avg_cpa": 37.51,
    "avg_roas": 0.75
  },
  "campaigns": [
    {
      "name": "CPAcademia | PixelSuscrip | Ventas | CBO | 5Conceptos | 21 Abril Activar",
      "status": "ACTIVE",
      "objective": "OUTCOME_SALES",
      "daily_budget": null,
      "lifetime_budget": null,
      "budget_remaining": 0
    },
    {
      "name": "CPAcademia | PixelSuscrip | Ventas | CBO Test | TopCreatives | 18 Abril",
      "status": "ACTIVE",
      "objective": "OUTCOME_SALES",
      "daily_budget": 50,
      "lifetime_budget": null,
      "budget_remaining": 21.69
    },
    {
      "name": "CPAcademia | PixelSuscrip | Ventas | Master ABO | Empizadropoptotal | 21 Marzo",
      "status": "ACTIVE",
      "objective": "OUTCOME_SALES",
      "daily_budget": null,
      "lifetime_budget": null,
      "budget_remaining": 0
    },
    {
      "name": "CPAcademia | PixelSuscrip | Ventas | Master ABO | Droptotal | 18 Marzo",
      "status": "PAUSED",
      "objective": "OUTCOME_SALES",
      "daily_budget": null,
      "lifetime_budget": null,
      "budget_remaining": 0
    },
    {
      "name": "CPAcademia | PixelSuscrip | Landing Curso. | Ventas | Master ABO | Droptotal | 11 Marzo",
      "status": "PAUSED",
      "objective": "OUTCOME_SALES",
      "daily_budget": null,
      "lifetime_budget": null,
      "budget_remaining": 0
    },
    {
      "name": "CPAcademia | PixelSuscrip | Ventas | Master ABO | Droptotal | 18 Feb",
      "status": "PAUSED",
      "objective": "OUTCOME_SALES",
      "daily_budget": null,
      "lifetime_budget": null,
      "budget_remaining": 0
    },
    {
      "name": "Leads | Lanzamiento Enero 2026 Master ABO | CO | VSL | 19 Enero",
      "status": "PAUSED",
      "objective": "OUTCOME_LEADS",
      "daily_budget": null,
      "lifetime_budget": null,
      "budget_remaining": 0
    }
  ],
  "insights": [
    {
      "campaign_name": "CPAcademia | PixelSuscrip | Ventas | Master ABO | Empizadropoptotal | 21 Marzo",
      "campaign_id": "120241959986740335",
      "adset_name": "USuscri | C | CO | Abierto | 22 marzo",
      "adset_id": "120241959986730335",
      "spend": 29.02,
      "impressions": 2913,
      "reach": 2118,
      "clicks": 40,
      "cpm": 9.962238,
      "cpc": 0.7255,
      "ctr": 1.373155,
      "frequency": 1.375354,
      "purchases": 1,
      "leads": 3,
      "initiate_checkout": 1,
      "add_to_cart": 0,
      "cost_per_purchase": 29.02,
      "roas": 0.972088
    },
    {
      "campaign_name": "CPAcademia | PixelSuscrip | Ventas | Master ABO | Empizadropoptotal | 21 Marzo",
      "campaign_id": "120241959986740335",
      "adset_name": "USuscri | C | CO | Abierto |  | 9 Abril",
      "adset_id": "120242948265790335",
      "spend": 27.52,
      "impressions": 3708,
      "reach": 2537,
      "clicks": 65,
      "cpm": 7.421791,
      "cpc": 0.423385,
      "ctr": 1.752967,
      "frequency": 1.461569,
      "purchases": 0,
      "leads": 1,
      "initiate_checkout": 1,
      "add_to_cart": 0,
      "cost_per_purchase": 0,
      "roas": 0
    },
    {
      "campaign_name": "CPAcademia | PixelSuscrip | Ventas | CBO Test | TopCreatives | 18 Abril",
      "campaign_id": "120243369739880335",
      "adset_name": "USuscri | C | CO | Abierto | Clon Broad | 18 Abril",
      "adset_id": "120243369740310335",
      "spend": 19.79,
      "impressions": 2408,
      "reach": 1865,
      "clicks": 25,
      "cpm": 8.218439,
      "cpc": 0.7916,
      "ctr": 1.038206,
      "frequency": 1.291153,
      "purchases": 2,
      "leads": 2,
      "initiate_checkout": 2,
      "add_to_cart": 0,
      "cost_per_purchase": 9.895,
      "roas": 2.85043
    },
    {
      "campaign_name": "CPAcademia | PixelSuscrip | Ventas | CBO | 5Conceptos | 21 Abril Activar",
      "campaign_id": "120243497487380335",
      "adset_name": "USuscri | C5 | CO | Interaccion IG 90d | 21 Abril",
      "adset_id": "120243497513940335",
      "spend": 14.46,
      "impressions": 2495,
      "reach": 1552,
      "clicks": 56,
      "cpm": 5.795591,
      "cpc": 0.258214,
      "ctr": 2.244489,
      "frequency": 1.607603,
      "purchases": 0,
      "leads": 0,
      "initiate_checkout": 0,
      "add_to_cart": 0,
      "cost_per_purchase": 0,
      "roas": 0
    },
    {
      "campaign_name": "CPAcademia | PixelSuscrip | Ventas | CBO | 5Conceptos | 21 Abril Activar",
      "campaign_id": "120243497487380335",
      "adset_name": "USuscri | C2 | CO | LAL Compradores | 21 Abril",
      "adset_id": "120243497488670335",
      "spend": 13.22,
      "impressions": 1959,
      "reach": 1456,
      "clicks": 51,
      "cpm": 6.748341,
      "cpc": 0.259216,
      "ctr": 2.603369,
      "frequency": 1.345467,
      "purchases": 0,
      "leads": 0,
      "initiate_checkout": 0,
      "add_to_cart": 0,
      "cost_per_purchase": 0,
      "roas": 0
    },
    {
      "campaign_name": "CPAcademia | PixelSuscrip | Ventas | CBO Test | TopCreatives | 18 Abril",
      "campaign_id": "120243369739880335",
      "adset_name": "USuscri | C | CO | Abierto | LAL InitiateCheckout | 18 Abril",
      "adset_id": "120243369743930335",
      "spend": 8.31,
      "impressions": 850,
      "reach": 628,
      "clicks": 94,
      "cpm": 9.776471,
      "cpc": 0.088404,
      "ctr": 11.058824,
      "frequency": 1.353503,
      "purchases": 0,
      "leads": 0,
      "initiate_checkout": 0,
      "add_to_cart": 0,
      "cost_per_purchase": 0,
      "roas": 0
    },
    {
      "campaign_name": "CPAcademia | PixelSuscrip | Ventas | CBO Test | TopCreatives | 18 Abril",
      "campaign_id": "120243369739880335",
      "adset_name": "USuscri | C | CO | Abierto | LAL Compradores | 18 Abril",
      "adset_id": "120243369742060335",
      "spend": 0.21,
      "impressions": 22,
      "reach": 21,
      "clicks": 3,
      "cpm": 9.545455,
      "cpc": 0.07,
      "ctr": 13.636364,
      "frequency": 1.047619,
      "purchases": 0,
      "leads": 0,
      "initiate_checkout": 0,
      "add_to_cart": 0,
      "cost_per_purchase": 0,
      "roas": 0
    }
  ]
}