{
  "account": {
    "id": "act_1326515245073322",
    "name": "Unlocked 4 ",
    "status": "ACTIVE",
    "currency": "USD"
  },
  "period": "today",
  "level": "adset",
  "summary": {
    "total_spend": 54.77,
    "total_purchases": 0,
    "total_revenue_estimated": 0,
    "avg_cpa": null,
    "avg_roas": 0
  },
  "campaigns": [
    {
      "name": "UA4 | CP | Pixel 1 | Master CBO | Testimonios | CO | VSL | 27 Marzo",
      "status": "PAUSED",
      "objective": "OUTCOME_LEADS",
      "daily_budget": 60,
      "lifetime_budget": null,
      "budget_remaining": 60
    },
    {
      "name": "UA4 | CP | Pixel 1 | Master ABO | Testimonios | CO | VSL |15 Marzo | Activar",
      "status": "ACTIVE",
      "objective": "OUTCOME_LEADS",
      "daily_budget": null,
      "lifetime_budget": null,
      "budget_remaining": 0
    },
    {
      "name": "UA4 | CP | Pixel 2 | Master CBO ABO | Ads DIC 22 | VSL | 19 Enero",
      "status": "PAUSED",
      "objective": "OUTCOME_LEADS",
      "daily_budget": 49.19,
      "lifetime_budget": null,
      "budget_remaining": 49.19
    },
    {
      "name": "Clientes potenciales | Programar | Master CBO ABO | Ads DIC 22 | VSL | 19 Enero",
      "status": "PAUSED",
      "objective": "OUTCOME_LEADS",
      "daily_budget": 40,
      "lifetime_budget": null,
      "budget_remaining": 40
    },
    {
      "name": "UA4 | CP | Pixel 1 | Master CBO | CO | VSL |19 Enero",
      "status": "PAUSED",
      "objective": "OUTCOME_LEADS",
      "daily_budget": 53.76,
      "lifetime_budget": null,
      "budget_remaining": 53.76
    }
  ],
  "insights": [
    {
      "campaign_name": "UA4 | CP | Pixel 1 | Master ABO | Testimonios | CO | VSL |15 Marzo | Activar",
      "campaign_id": "120245470534520119",
      "adset_name": "Testimonios | Programar | CO | Exclu Leads 180 - Abierto | 15 Abril",
      "adset_id": "120247197906800119",
      "spend": 31.01,
      "impressions": 1935,
      "reach": 1528,
      "clicks": 234,
      "cpm": 16.02584,
      "cpc": 0.132521,
      "ctr": 12.093023,
      "frequency": 1.266361,
      "purchases": 0,
      "leads": 3,
      "initiate_checkout": 0,
      "add_to_cart": 0,
      "cost_per_purchase": 0,
      "roas": 0
    },
    {
      "campaign_name": "UA4 | CP | Pixel 1 | Master ABO | Testimonios | CO | VSL |15 Marzo | Activar",
      "campaign_id": "120245470534520119",
      "adset_name": "Testimonios | Programar | CO | Exclu Leads 180 - Abierto | 15 Marzo",
      "adset_id": "120245470534550119",
      "spend": 23.76,
      "impressions": 1092,
      "reach": 861,
      "clicks": 79,
      "cpm": 21.758242,
      "cpc": 0.300759,
      "ctr": 7.234432,
      "frequency": 1.268293,
      "purchases": 0,
      "leads": 0,
      "initiate_checkout": 0,
      "add_to_cart": 0,
      "cost_per_purchase": 0,
      "roas": 0
    }
  ]
}