{
  "account": {
    "id": "act_1833510890685857",
    "name": "Unlocked Low Ticket 1",
    "status": "ACTIVE",
    "currency": "USD"
  },
  "period": "today",
  "level": "adset",
  "summary": {
    "total_spend": 161.61,
    "total_purchases": 1,
    "total_revenue_estimated": 28.21,
    "avg_cpa": 161.61,
    "avg_roas": 0.17
  },
  "campaigns": [
    {
      "name": "CPAcademia | PixelSuscrip | Ventas | Master ABO | Sistema 5 Creativos | 28 Abril",
      "status": "ACTIVE",
      "objective": "OUTCOME_SALES",
      "daily_budget": null,
      "lifetime_budget": null,
      "budget_remaining": 0
    },
    {
      "name": "CPAcademia | PixelSuscrip | Ventas | CBO | 5Conceptos | 21 Abril Activar",
      "status": "ACTIVE",
      "objective": "OUTCOME_SALES",
      "daily_budget": null,
      "lifetime_budget": null,
      "budget_remaining": 0
    },
    {
      "name": "CPAcademia | PixelSuscrip | Ventas | CBO Test | TopCreatives | 18 Abril",
      "status": "ACTIVE",
      "objective": "OUTCOME_SALES",
      "daily_budget": 20,
      "lifetime_budget": null,
      "budget_remaining": 0
    },
    {
      "name": "CPAcademia | PixelSuscrip | Ventas | Master ABO | Empizadropoptotal | 21 Marzo",
      "status": "ACTIVE",
      "objective": "OUTCOME_SALES",
      "daily_budget": null,
      "lifetime_budget": null,
      "budget_remaining": 0
    },
    {
      "name": "CPAcademia | PixelSuscrip | Ventas | Master ABO | Droptotal | 18 Marzo",
      "status": "PAUSED",
      "objective": "OUTCOME_SALES",
      "daily_budget": null,
      "lifetime_budget": null,
      "budget_remaining": 0
    },
    {
      "name": "CPAcademia | PixelSuscrip | Landing Curso. | Ventas | Master ABO | Droptotal | 11 Marzo",
      "status": "PAUSED",
      "objective": "OUTCOME_SALES",
      "daily_budget": null,
      "lifetime_budget": null,
      "budget_remaining": 0
    },
    {
      "name": "CPAcademia | PixelSuscrip | Ventas | Master ABO | Droptotal | 18 Feb",
      "status": "PAUSED",
      "objective": "OUTCOME_SALES",
      "daily_budget": null,
      "lifetime_budget": null,
      "budget_remaining": 0
    },
    {
      "name": "Leads | Lanzamiento Enero 2026 Master ABO | CO | VSL | 19 Enero",
      "status": "PAUSED",
      "objective": "OUTCOME_LEADS",
      "daily_budget": null,
      "lifetime_budget": null,
      "budget_remaining": 0
    }
  ],
  "insights": [
    {
      "campaign_name": "CPAcademia | PixelSuscrip | Ventas | Master ABO | Sistema 5 Creativos | 28 Abril",
      "campaign_id": "120243883867660335",
      "adset_name": "USuscri | C | CO | Abierto | Sistema 5 Creativos | 28 Abril",
      "adset_id": "120243884243490335",
      "spend": 40.69,
      "impressions": 7738,
      "reach": 5132,
      "clicks": 62,
      "cpm": 5.258465,
      "cpc": 0.65629,
      "ctr": 0.801241,
      "frequency": 1.507794,
      "purchases": 0,
      "leads": 1,
      "initiate_checkout": 2,
      "add_to_cart": 0,
      "cost_per_purchase": 0,
      "roas": 0
    },
    {
      "campaign_name": "CPAcademia | PixelSuscrip | Ventas | Master ABO | Empizadropoptotal | 21 Marzo",
      "campaign_id": "120241959986740335",
      "adset_name": "USuscri | C | CO | Abierto | 22 marzo",
      "adset_id": "120241959986730335",
      "spend": 40.21,
      "impressions": 3308,
      "reach": 2115,
      "clicks": 42,
      "cpm": 12.155381,
      "cpc": 0.957381,
      "ctr": 1.269649,
      "frequency": 1.564066,
      "purchases": 0,
      "leads": 0,
      "initiate_checkout": 0,
      "add_to_cart": 0,
      "cost_per_purchase": 0,
      "roas": 0
    },
    {
      "campaign_name": "CPAcademia | PixelSuscrip | Ventas | CBO | 5Conceptos | 21 Abril Activar",
      "campaign_id": "120243497487380335",
      "adset_name": "USuscri | C5 | CO | Interaccion IG 90d | 21 Abril",
      "adset_id": "120243497513940335",
      "spend": 23.02,
      "impressions": 3720,
      "reach": 1659,
      "clicks": 76,
      "cpm": 6.188172,
      "cpc": 0.302895,
      "ctr": 2.043011,
      "frequency": 2.242315,
      "purchases": 0,
      "leads": 0,
      "initiate_checkout": 0,
      "add_to_cart": 0,
      "cost_per_purchase": 0,
      "roas": 0
    },
    {
      "campaign_name": "CPAcademia | PixelSuscrip | Ventas | CBO | 5Conceptos | 21 Abril Activar",
      "campaign_id": "120243497487380335",
      "adset_name": "USuscri | C2 | CO | LAL Compradores | 21 Abril",
      "adset_id": "120243497488670335",
      "spend": 18.42,
      "impressions": 2294,
      "reach": 1416,
      "clicks": 102,
      "cpm": 8.029643,
      "cpc": 0.180588,
      "ctr": 4.446382,
      "frequency": 1.620057,
      "purchases": 0,
      "leads": 0,
      "initiate_checkout": 0,
      "add_to_cart": 0,
      "cost_per_purchase": 0,
      "roas": 0
    },
    {
      "campaign_name": "CPAcademia | PixelSuscrip | Ventas | CBO Test | TopCreatives | 18 Abril",
      "campaign_id": "120243369739880335",
      "adset_name": "USuscri | C | CO | Abierto | Clon Broad | 18 Abril",
      "adset_id": "120243369740310335",
      "spend": 14.85,
      "impressions": 3249,
      "reach": 2493,
      "clicks": 50,
      "cpm": 4.570637,
      "cpc": 0.297,
      "ctr": 1.538935,
      "frequency": 1.303249,
      "purchases": 1,
      "leads": 3,
      "initiate_checkout": 2,
      "add_to_cart": 0,
      "cost_per_purchase": 14.85,
      "roas": 1.899663
    },
    {
      "campaign_name": "CPAcademia | PixelSuscrip | Ventas | CBO Test | TopCreatives | 18 Abril",
      "campaign_id": "120243369739880335",
      "adset_name": "USuscri | C | CO | Abierto | LAL Compradores | 18 Abril",
      "adset_id": "120243369742060335",
      "spend": 13.13,
      "impressions": 1405,
      "reach": 948,
      "clicks": 122,
      "cpm": 9.345196,
      "cpc": 0.107623,
      "ctr": 8.683274,
      "frequency": 1.482068,
      "purchases": 0,
      "leads": 0,
      "initiate_checkout": 0,
      "add_to_cart": 0,
      "cost_per_purchase": 0,
      "roas": 0
    },
    {
      "campaign_name": "CPAcademia | PixelSuscrip | Ventas | Master ABO | Sistema 5 Creativos | 28 Abril",
      "campaign_id": "120243883867660335",
      "adset_name": "USuscri | C | CO | Broad Winners Clone | 2 Mayo",
      "adset_id": "120244124464370335",
      "spend": 11.29,
      "impressions": 1908,
      "reach": 1152,
      "clicks": 24,
      "cpm": 5.917191,
      "cpc": 0.470417,
      "ctr": 1.257862,
      "frequency": 1.65625,
      "purchases": 0,
      "leads": 1,
      "initiate_checkout": 1,
      "add_to_cart": 0,
      "cost_per_purchase": 0,
      "roas": 0
    }
  ]
}